[
  {
    "id": "lore_qin_juezhi",
    "era": "秦朝",
    "topic": "爵制",
    "title": "二十等爵制",
    "content": "秦朝实行二十等军功爵制，按军功大小授予爵位：一级公士、二级上造、三级簪袅、四级不更、五大夫、左庶长、右庶长、左更、中更、右更、少上造、大上造、驷车庶长、大庶长、关内侯、彻侯。军功爵与田宅、奴婢、官职直接挂钩，是秦朝社会流动的核心制度。无军功者不得授爵，宗室若无军功亦不得入属籍。斩首一级授爵一级，赐田一顷、宅九亩。",
    "tags": [
      "社会制度",
      "军功",
      "爵位"
    ],
    "createdAt": "2026-04-14T00:00:00.000Z"
  },
  {
    "id": "lore_qin_junxian",
    "era": "秦朝",
    "topic": "政治制度",
    "title": "郡县制",
    "content": "秦统一六国后废除分封制，全面推行郡县制。全国分为三十六郡（后增至四十余郡），郡设守、尉、监。郡下设县，万户以上为县令，万户以下为县长。县下设乡、里。官员由中央直接任免，不得世袭。郡县制是中央集权的基础制度，确保政令统一传达执行。",
    "tags": [
      "政治制度",
      "中央集权",
      "行政区划"
    ],
    "createdAt": "2026-04-14T00:00:00.000Z"
  },
  {
    "id": "lore_qin_fajia",
    "era": "秦朝",
    "topic": "思想",
    "title": "法家思想核心",
    "content": "秦以法家思想治国，核心为：一、以法治国，法令统一，信赏必罚；二、以吏为师，禁私学，焚书坑儒以统一思想；三、重农抑商，奖励耕织，以农战为本；四、愚民弱民，使民专心于农战；五、尊主卑臣，强化君权至上。商鞅变法奠定基础，韩非集法家大成。法家三派：商鞅之法、申不害之术、慎到之势，秦始皇兼收并用。",
    "tags": [
      "思想",
      "法家",
      "治国理念"
    ],
    "createdAt": "2026-04-14T00:00:00.000Z"
  },
  {
    "id": "lore_qin_liyi",
    "era": "秦朝",
    "topic": "礼仪",
    "title": "礼仪制度",
    "content": "秦朝礼仪制度融合六国礼制并有所创新：一、上朝礼仪，群臣朝拜须三呼万岁，行跪拜礼；二、舆服制度，天子乘六马、服黑色（秦尚水德），不同爵位对应不同服饰规格；三、祭祀礼仪，祭天于雍，祭地于汾阴，封禅泰山；四、相见礼节，臣见君须行顿首礼，平交行空首礼；五、冠礼、婚礼、丧礼均有严格等级规定。违礼者轻则罚金，重则黥面为城旦。",
    "tags": [
      "礼仪",
      "等级制度",
      "祭祀"
    ],
    "createdAt": "2026-04-14T00:00:00.000Z"
  },
  {
    "id": "lore_qin_bingqi",
    "era": "秦朝",
    "topic": "军事",
    "title": "兵器规格",
    "content": "秦军兵器标准化程度极高：一、青铜剑，标准长约86-94厘米，采用复合剑铸造工艺，锋利坚硬；二、弩机，全国统一规格，部件可互换，射程约200-300米；三、戈矛，戈长约2.7-3米，矛长约4-5米；四、秦弩箭镞呈三棱形，统一规格，杀伤力强；五、铠甲为石片甲，方甲片编缀，分步兵甲与骑兵甲。秦军编制以五人为伍，设伍长，十伍为什，百人为百将。兵器上刻有工匠姓名，实行质量追溯制度。",
    "tags": [
      "军事",
      "兵器",
      "标准化"
    ],
    "createdAt": "2026-04-14T00:00:00.000Z"
  },
  {
    "id": "lore_qin_guanzhi",
    "era": "秦朝",
    "topic": "官职",
    "title": "官职体系",
    "content": "秦朝中央官制为三公九卿制：三公——丞相（百官之首，总理政务）、太尉（掌军事）、御史大夫（副相，掌监察）；九卿——奉常（掌宗庙礼仪）、郎中令（掌宫殿侍卫）、卫尉（掌宫门卫兵）、太仆（掌车马）、廷尉（掌司法）、典客（掌外交）、宗正（掌宗室事务）、治粟内史（掌财政）、少府（掌皇室财政）。地方官制：郡守（郡级行政长官）、郡尉（郡级军事长官）、郡监（郡级监察）、县令/县长（县级行政长官）。",
    "tags": [
      "官职",
      "政治制度",
      "三公九卿"
    ],
    "createdAt": "2026-04-14T00:00:00.000Z"
  }
]