[
  {
    "id": "story_1_荆轲刺秦王",
    "title": "荆轲刺秦王",
    "description": "基于荆轲刺秦王历史事件的故事续写平台，探索不同历史转折点",
    "author": "历史故事组",
    "createdAt": "2026-04-12T09:59:44.221Z",
    "updatedAt": "2026-04-17T10:12:29.571Z",
    "characterIds": [
      "char_mnzwozgz_xb5tn0",
      "char_mnzwozh2_s4ep5q",
      "char_mnzwozh2_h2lsum",
      "char_mnzwozh2_ednzgg",
      "char_mnzwozh2_ay0kep"
    ],
    "genre": "正史",
    "era": "战国"
  },
  {
    "id": "story_2_赤壁之战",
    "title": "赤壁之战",
    "description": "基于赤壁之战历史事件的故事续写平台，重新演绎三国历史",
    "author": "历史故事组",
    "createdAt": "2026-04-12T09:59:44.228Z",
    "updatedAt": "2026-04-12T09:59:44.228Z",
    "characterIds": [
      "char_mnzwozh2_guemh1",
      "char_mnzwozh2_9zffon",
      "char_mnzwozh2_29nylj",
      "char_mnzwozh2_lizol7",
      "char_mnzwozh2_pzq6f1",
      "char_mnzwozh2_g9p1sj"
    ]
  },
  {
    "id": "story_3_玄武门之变",
    "title": "玄武门之变",
    "description": "基于玄武门之变历史事件的故事续写平台，改变唐朝历史走向",
    "author": "历史故事组",
    "createdAt": "2026-04-12T09:59:44.228Z",
    "updatedAt": "2026-04-12T09:59:44.228Z",
    "characterIds": [
      "char_mnzwozh2_jjin7b",
      "char_mnzwozh3_kxf26f",
      "char_mnzwozh3_2lfrzo",
      "char_mnzwozh3_xgig5j",
      "char_mnzwozh3_xq9kc7",
      "char_mnzwozh3_xdseh4"
    ]
  },
  {
    "id": "story_1775994497022_q94ao4wql",
    "title": "卧龙没有出山",
    "description": "三国时期诸葛亮没有出山",
    "author": "dfsaf",
    "createdAt": "2026-04-12T11:48:17.022Z",
    "updatedAt": "2026-04-12T11:48:17.022Z"
  },
  {
    "id": "story_1776401926668_wt100dv7t",
    "title": "宇智波带土的重生",
    "description": "火影忍者同人，带土重生带着双万花筒写轮眼回到了9岁，上忍者学校，他带着前世的记忆",
    "author": "buyaoxiantale",
    "createdAt": "2026-04-17T04:58:46.668Z",
    "updatedAt": "2026-04-17T10:12:33.404Z",
    "rootSegmentId": "seg_1776401926668_7fpj7z8jb",
    "genre": "同人",
    "era": "火影忍者"
  },
  {
    "id": "story_1776444664307_2aglm3coj",
    "title": "三体",
    "description": "在三体中，叶文洁最后没有摁下那个发射按钮，而是选择了原谅过去正常的生活",
    "author": "mapi",
    "createdAt": "2026-04-17T16:51:04.307Z",
    "updatedAt": "2026-04-18T12:14:28.973Z",
    "rootSegmentId": "seg_1776444664308_cka6i5o37",
    "genre": "科幻",
    "era": "现代"
  }
]